{
  "@type" : "sc:AnnotationList",
  "resources" : [ {
    "resource" : [ {
      "http://dev.llgc.org.uk/sas/full_text" : "<span style=\"color: #4d5156; font-family: arial, sans-serif;\">Leonard Bridgman's atmospheric wash paintings with Oliver Stewart's lively commentary on these Great War machines make this an aviation classic. Originall published in 1938.",
      "@type" : "dctypes:Text",
      "format" : "text/html",
      "chars" : "<p><span style=\"color: #4d5156; font-family: arial, sans-serif;\">Leonard Bridgman's atmospheric wash paintings with Oliver Stewart's lively commentary on these Great War machines make this an aviation classic. Originall published in 1938.</span></p>"
    } ],
    "@type" : "oa:Annotation",
    "dcterms:creator" : "https://dev.gdmrdigital.com/user/1245635613/102290604",
    "motivation" : [ "oa:commenting" ],
    "dcterms:created" : "2022-03-24T11:48:44",
    "@id" : "https://dev.gdmrdigital.com/annotation/anno/1648122524717",
    "dcterms:modified" : "2022-03-24T11:48:44",
    "@context" : "file:/usr/local/tomcat/webapps/ROOT/contexts/iiif-2.0.json",
    "on" : [ {
      "within" : {
        "@type" : "sc:Manifest",
        "@id" : "https://EveOes.github.io/Eveproject/manifests/manifest2.json"
      },
      "@type" : "oa:SpecificResource",
      "selector" : {
        "default" : {
          "@type" : "oa:FragmentSelector",
          "value" : "xywh=355,506,1614,165"
        },
        "item" : {
          "@type" : "oa:SvgSelector",
          "value" : "<svg xmlns='http://www.w3.org/2000/svg'><path xmlns=\"http://www.w3.org/2000/svg\" d=\"M354.70617,506.18654h807.18794v0h807.18794v82.57854v82.57854h-807.18794h-807.18794v-82.57854z\" data-paper-data=\"{&quot;strokeWidth&quot;:1,&quot;rotation&quot;:0,&quot;deleteIcon&quot;:null,&quot;rotationIcon&quot;:null,&quot;group&quot;:null,&quot;editable&quot;:true,&quot;annotation&quot;:null}\" id=\"rectangle_0056ebc4-acbf-418d-bf75-f8d03a5eecc6\" fill-opacity=\"0\" fill=\"#00bfff\" fill-rule=\"nonzero\" stroke=\"#00bfff\" stroke-width=\"1\" stroke-linecap=\"butt\" stroke-linejoin=\"miter\" stroke-miterlimit=\"10\" stroke-dasharray=\"\" stroke-dashoffset=\"0\" font-family=\"none\" font-weight=\"none\" font-size=\"none\" text-anchor=\"none\" style=\"mix-blend-mode: normal\"/></svg>"
        },
        "@type" : "oa:Choice"
      },
      "full" : "http://f4b69252-650b-4229-a2ad-b7e62271ee10"
    } ]
  } ],
  "@id" : "https://EveOes.github.io/Eveproject/annotations/titlepageannotations.json",
  "@context" : "http://iiif.io/api/presentation/2/context.json"
}